setup.py
pintail/__init__.py
pintail/elasticsearch/__init__.py
pintail/elasticsearch/pintail-elasticsearch.page
pintail/elasticsearch/pintail-elasticsearch.xsl
pintail_elasticsearch.egg-info/PKG-INFO
pintail_elasticsearch.egg-info/SOURCES.txt
pintail_elasticsearch.egg-info/dependency_links.txt
pintail_elasticsearch.egg-info/namespace_packages.txt
pintail_elasticsearch.egg-info/requires.txt
pintail_elasticsearch.egg-info/top_level.txt