Metadata-Version: 1.1
Name: pintail-elasticsearch
Version: 0.3
Summary: Use Elasticsearch on Pintail sites.
Home-page: UNKNOWN
Author: Shaun McCance
Author-email: shaunm@gnome.org
License: GPLv2+
Platform: UNKNOWN
Classifier: Development Status :: 3 - Alpha
Classifier: Environment :: Console
Classifier: Programming Language :: Python :: 3
Classifier: Programming Language :: Python :: 3 :: Only
Classifier: Topic :: Documentation
Classifier: Topic :: Software Development :: Documentation
Classifier: Topic :: Text Processing :: Markup
Classifier: Topic :: Text Processing :: Markup :: XML
Classifier: License :: OSI Approved :: GNU General Public License v2 or later (GPLv2+)
